README.md
setup.py
bayserver_docker_wordpress/__init__.py
bayserver_docker_wordpress/word_press_docker.py
bayserver_docker_wordpress.egg-info/PKG-INFO
bayserver_docker_wordpress.egg-info/SOURCES.txt
bayserver_docker_wordpress.egg-info/dependency_links.txt
bayserver_docker_wordpress.egg-info/requires.txt
bayserver_docker_wordpress.egg-info/top_level.txt