Metadata-Version: 1.2
Name: bayserver-docker-wordpress
Version: 2.3.4
Summary: WordPress docker for BayServer
Home-page: https://baykit.yokohama/
Author: Michisuke-P
Author-email: michisukep@gmail.com
License: MIT
Platform: UNKNOWN
Requires-Python: >=3.7
